sparsegpt/__init__.py
sparsegpt-0.0.1.dev0.dist-info/METADATA
sparsegpt-0.0.1.dev0.dist-info/WHEEL
sparsegpt-0.0.1.dev0.dist-info/top_level.txt
sparsegpt-0.0.1.dev0.dist-info/RECORD
