Metadata-Version: 2.1
Name: sparsegpt
Version: 0.0.1.dev0
Summary: sparsegpt - Massive Language Models Can be Accurately Pruned in One-shot
Author: Shadow Walker
Keywords: sparsegpt
Classifier: Programming Language :: Python :: 3
Classifier: Programming Language :: Python :: 3.8
Classifier: Programming Language :: Python :: 3.9
Classifier: Programming Language :: Python :: 3.10
Requires-Dist: torch
